jwa/__init__.py
jwa-2022.1.dist-info/entry_points.txt
jwa-2022.1.dist-info/WHEEL
jwa-2022.1.dist-info/METADATA
jwa-2022.1.dist-info/RECORD
